zuadoss/__init__.py
zuadoss/auth.py
zuadoss/bucket.py
zuadoss/exceptions.py
zuadoss/models.py
zuadoss-1.0.2.dist-info/licenses/LICENSE
zuadoss-1.0.2.dist-info/METADATA
zuadoss-1.0.2.dist-info/WHEEL
zuadoss-1.0.2.dist-info/top_level.txt
zuadoss-1.0.2.dist-info/RECORD
