Metadata-Version: 2.4
Name: zuadoss
Version: 1.0.2
Summary: ZUAD OSS Python SDK - 兼容OSS接口的对象存储Python客户端SDK
Home-page: https://github.com/zuadoss/zuadoss-python-sdk
Author: ZUAD OSS Team
Author-email: ZUAD OSS Team <support@zuadoss.com>
License: MIT
Project-URL: Homepage, https://zuadoss.com
Project-URL: Documentation, https://zuadoss.readthedocs.io/
Project-URL: Repository, https://github.com/zuadoss/zuadoss-python-sdk
Project-URL: Bug Reports, https://github.com/zuadoss/zuadoss-python-sdk/issues
Keywords: oss,object-storage,cloud-storage,s3-compatible,zuad,zuadoss,storage,sdk,python
Classifier: Development Status :: 4 - Beta
Classifier: Intended Audience :: Developers
Classifier: License :: OSI Approved :: MIT License
Classifier: Operating System :: OS Independent
Classifier: Programming Language :: Python :: 3
Classifier: Programming Language :: Python :: 3.7
Classifier: Programming Language :: Python :: 3.8
Classifier: Programming Language :: Python :: 3.9
Classifier: Programming Language :: Python :: 3.10
Classifier: Programming Language :: Python :: 3.11
Classifier: Programming Language :: Python :: 3.12
Classifier: Topic :: Internet :: WWW/HTTP
Classifier: Topic :: Software Development :: Libraries :: Python Modules
Classifier: Topic :: System :: Archiving
Classifier: Topic :: Utilities
Requires-Python: >=3.7
License-File: LICENSE
Requires-Dist: requests>=2.25.0
Dynamic: author
Dynamic: home-page
Dynamic: license-file
Dynamic: requires-python
